LICENSE.txt
MANIFEST.in
README.md
setup.py
lib/ActivePapers.Py.egg-info/PKG-INFO
lib/ActivePapers.Py.egg-info/SOURCES.txt
lib/ActivePapers.Py.egg-info/dependency_links.txt
lib/ActivePapers.Py.egg-info/top_level.txt
lib/activepapers/__init__.py
lib/activepapers/builtins2.py
lib/activepapers/builtins3.py
lib/activepapers/cli.py
lib/activepapers/contents.py
lib/activepapers/execution.py
lib/activepapers/exploration.py
lib/activepapers/library.py
lib/activepapers/standardlib.py
lib/activepapers/standardlib2.py
lib/activepapers/standardlib3.py
lib/activepapers/storage.py
lib/activepapers/url.py
lib/activepapers/url2.py
lib/activepapers/url3.py
lib/activepapers/utility.py
lib/activepapers/utility2.py
lib/activepapers/utility3.py
lib/activepapers/version.py
scripts/aptool
tests/test_basics.py
tests/test_exploration.py
tests/test_features.py
tests/test_library.py
tests/test_python_modules.py
tests/test_references.py
tests/foo/__init__.py
tests/foo/bar.py