Metadata-Version: 1.1
Name: ActivePapers.Py
Version: 0.2.2
Summary: Executable papers containing Python code
Home-page: http://github.com/activepapers/activepapers-python
Author: Konrad Hinsen
Author-email: research@khinsen.fastmail.net
License: BSD
Platform: any
Classifier: Development Status :: 3 - Alpha
Classifier: Intended Audience :: Science/Research
Classifier: License :: OSI Approved :: BSD License
Classifier: Operating System :: OS Independent
Classifier: Programming Language :: Python :: 2.7
Classifier: Programming Language :: Python :: 3.4
Classifier: Programming Language :: Python :: 3.5
Classifier: Programming Language :: Python :: 3.6
Classifier: Topic :: Scientific/Engineering
Requires: numpy (>=1.6)
Requires: h5py (>=2.2)
Requires: tempdir (>=0.6)
Provides: ActivePapers
